flask_demo_helper/__init__.py
flask_demo_helper/module1.py
flask_demo_helper/module2.py
flask_demo_helper/module3.py
flask_demo_helper/module4.py
flask_demo_helper/module5.py
flask_demo_helper/module6.py
flask_demo_helper/module7.py
flask_demo_helper/module8.py
flask_demo_helper/module9.py
flask_demo_helper-0.2.0.dist-info/LICENSE
flask_demo_helper-0.2.0.dist-info/METADATA
flask_demo_helper-0.2.0.dist-info/WHEEL
flask_demo_helper-0.2.0.dist-info/top_level.txt
flask_demo_helper-0.2.0.dist-info/RECORD
