Metadata-Version: 2.1
Name: flask-demo-helper
Version: 0.2.0
Summary: A library that provides examples and solutions for common tasks in Flask applications
Home-page: https://github.com/rathe12/flask-demo-helper
Author: rathe12
Author-email: markzerone1@gmail.com
License: UNKNOWN
Platform: UNKNOWN
Classifier: Programming Language :: Python :: 3
Classifier: License :: OSI Approved :: MIT License
Classifier: Operating System :: OS Independent
Requires-Python: >=3.6
License-File: LICENSE
Requires-Dist: Flask >=1.1.2
